cmip6_downscaling/__init__.py
cmip6_downscaling/_version.py
cmip6_downscaling/config.py
cmip6_downscaling/constants.py
cmip6_downscaling/runtimes.py
cmip6_downscaling/utils.py
cmip6_downscaling/analysis/__init__.py
cmip6_downscaling/analysis/analyses_template.ipynb
cmip6_downscaling/analysis/analysis.py
cmip6_downscaling/analysis/metrics.py
cmip6_downscaling/analysis/plot.py
cmip6_downscaling/analysis/qaqc.py
cmip6_downscaling/data/__init__.py
cmip6_downscaling/data/cmip.py
cmip6_downscaling/data/observations.py
cmip6_downscaling/data/utils.py
cmip6_downscaling/disagg/__init__.py
cmip6_downscaling/disagg/derived_variables.py
cmip6_downscaling/disagg/terraclimate.py
cmip6_downscaling/disagg/wrapper.py
cmip6_downscaling/methods/__init__.py
cmip6_downscaling/methods/bcsd/__init__.py
cmip6_downscaling/methods/bcsd/tasks.py
cmip6_downscaling/methods/bcsd/utils.py
cmip6_downscaling/methods/common/__init__.py
cmip6_downscaling/methods/common/bias_correction.py
cmip6_downscaling/methods/common/containers.py
cmip6_downscaling/methods/common/tasks.py
cmip6_downscaling/methods/common/utils.py
cmip6_downscaling/methods/deepsd/__init__.py
cmip6_downscaling/methods/deepsd/deepsd_config.ini
cmip6_downscaling/methods/deepsd/tasks.py
cmip6_downscaling/methods/deepsd/utils.py
cmip6_downscaling/methods/gard/__init__.py
cmip6_downscaling/methods/gard/tasks.py
cmip6_downscaling/methods/gard/utils.py
cmip6_downscaling/methods/maca/__init__.py
cmip6_downscaling/methods/maca/core.py
cmip6_downscaling/methods/maca/tasks.py
cmip6_downscaling/methods/maca/utils.py
cmip6_downscaling-1.1.1.dist-info/LICENSE
cmip6_downscaling-1.1.1.dist-info/METADATA
cmip6_downscaling-1.1.1.dist-info/WHEEL
cmip6_downscaling-1.1.1.dist-info/top_level.txt
cmip6_downscaling-1.1.1.dist-info/RECORD
