Metadata-Version: 2.1
Name: cmip6-downscaling
Version: 1.1.1
Summary: Climate downscaling using cmip6 data
Author-email: CarbonPlan <tech@carbonplan.org>
License: MIT
Project-URL: repository, https://github.com/carbonplan/cmip6-downscaling
Classifier: Development Status :: 4 - Beta
Classifier: License :: OSI Approved :: MIT License
Classifier: Operating System :: OS Independent
Classifier: Intended Audience :: Science/Research
Classifier: Programming Language :: Python
Classifier: Programming Language :: Python :: 3
Classifier: Programming Language :: Python :: 3.9
Classifier: Programming Language :: Python :: 3.10
Classifier: Topic :: Scientific/Engineering
Requires-Python: >=3.9
License-File: LICENSE
Requires-Dist: adlfs >=2022.2.0
Requires-Dist: carbonplan-data
Requires-Dist: carbonplan[styles]
Requires-Dist: cf-xarray >=0.7.3
Requires-Dist: cmip6-preprocessing
Requires-Dist: dask[complete]
Requires-Dist: dask-kubernetes
Requires-Dist: donfig >=0.7.0
Requires-Dist: fsspec
Requires-Dist: intake <=0.7.0
Requires-Dist: intake-esm >=2022.9.18
Requires-Dist: intake-xarray
Requires-Dist: ndpyramid ==0.0.6
Requires-Dist: pandas
Requires-Dist: prefect ==0.15.13
Requires-Dist: rechunker
Requires-Dist: regionmask
Requires-Dist: scikit-downscale >=0.1.2
Requires-Dist: scikit-learn
Requires-Dist: scipy
Requires-Dist: universal-pathlib >=0.0.12
Requires-Dist: xarray >=2022.3.0
Requires-Dist: xarray-datatree ==0.0.6
Requires-Dist: xarray-schema >=0.0.3
Requires-Dist: xclim
Requires-Dist: xesmf
Requires-Dist: zarr >=2.11.3
Provides-Extra: analysis
Requires-Dist: cartopy ; extra == 'analysis'
Requires-Dist: seaborn ; extra == 'analysis'
Requires-Dist: carbonplan[styles] ; extra == 'analysis'
Provides-Extra: deepsd
Requires-Dist: tensorflow ; extra == 'deepsd'
Requires-Dist: tensorflow-io ; extra == 'deepsd'
Provides-Extra: dev
Requires-Dist: pytest ; extra == 'dev'
Requires-Dist: pytest-sugar ; extra == 'dev'
Requires-Dist: pytest-cov ; extra == 'dev'
